weather_rp5/__init__.py
weather_rp5/cleanup.py
weather_rp5/downloader.py
weather_rp5/headers.py
weather_rp5/main.py
weather_rp5/utils.py
weather_rp5-1.4.dist-info/METADATA
weather_rp5-1.4.dist-info/WHEEL
weather_rp5-1.4.dist-info/top_level.txt
weather_rp5-1.4.dist-info/RECORD
