Metadata-Version: 2.4
Name: weather_rp5
Version: 1.4
Summary: Functions for retrieving weather data from rp5.ru
Home-page: https://github.com/jakmuell/weather_rp5/
Author: Jakob Müller
Author-email: jakob.mueller1004@gmail.com
Classifier: License :: OSI Approved :: MIT License
Classifier: Programming Language :: Python :: 3
Classifier: Operating System :: OS Independent
Requires-Dist: pandas
Requires-Dist: bs4
Requires-Dist: httpx
Dynamic: author
Dynamic: author-email
Dynamic: classifier
Dynamic: description
Dynamic: description-content-type
Dynamic: home-page
Dynamic: requires-dist
Dynamic: summary
